nexxclone
