Metadata-Version: 2.1
Name: nexxclone
Version: 1.1.1
Summary: A Discord Selfbot for Clone Discord Server
Home-page: https://github.com/noritem/nexx_clone
Author: nexxrar
Author-email: tech@moxx.tech
License: MIT
Keywords: discord selfbot clone nexxclone
Platform: UNKNOWN
Classifier: Programming Language :: Python :: 3.10
Classifier: License :: OSI Approved :: MIT License
